rusty_utils/__init__.py
rusty_utils/common.py
rusty_utils/option.py
rusty_utils/result.py
rusty_utils-0.1.5.dist-info/METADATA
rusty_utils-0.1.5.dist-info/WHEEL
rusty_utils-0.1.5.dist-info/RECORD
