Metadata-Version: 2.1
Name: rusty-utils
Version: 0.1.5
Summary: Bring some useful tools from Rust to Python
Home-page: https://github.com/iceice666/rusty-utils
License: MIT
Author: iceice666
Author-email: iceice666@outlook.com
Requires-Python: >=3.11,<4.0
Classifier: License :: OSI Approved :: MIT License
Classifier: Programming Language :: Python :: 3
Classifier: Programming Language :: Python :: 3.11
Classifier: Programming Language :: Python :: 3.12
Project-URL: Repository, https://github.com/iceice666/rusty-utils
